noted/__init__.py
noted/__main__.py
noted_fuadizza-0.1.0.dist-info/licenses/LICENSE
noted_fuadizza-0.1.0.dist-info/METADATA
noted_fuadizza-0.1.0.dist-info/WHEEL
noted_fuadizza-0.1.0.dist-info/entry_points.txt
noted_fuadizza-0.1.0.dist-info/top_level.txt
noted_fuadizza-0.1.0.dist-info/RECORD
